canvasim/__init__.py
canvasim/__version__.py
canvasim/canvas/__init__.py
canvasim/canvas/draw_utils.py
canvasim/canvas/edit_tool.py
canvasim/canvas/element.py
canvasim/canvas/handle.py
canvasim/canvas/transformation.py
canvasim/canvas/viewport.py
canvasim/canvas/world.py
canvasim/canvas/world_globals.py
canvasim/gui/__init__.py
canvasim/gui/color_utils.py
canvasim/gui/gui_context.py
canvasim/gui/gui_element.py
canvasim/gui/gui_globals.py
canvasim/gui/primitives.py
canvasim/gui/radio_button.py
canvasim/gui/slider.py
canvasim/gui/text_box.py
canvasim/gui/toggle_button.py
canvasim/shapes/__init__.py
canvasim/shapes/polygon.py
canvasim/shapes/polygon_tool.py
canvasim/shapes/rectangle.py
canvasim/shapes/rectangle_tool.py
canvasim-0.2.0.dist-info/licenses/LICENSE
canvasim-0.2.0.dist-info/METADATA
canvasim-0.2.0.dist-info/WHEEL
canvasim-0.2.0.dist-info/top_level.txt
canvasim-0.2.0.dist-info/RECORD
