Metadata-Version: 2.4
Name: canvasim
Version: 0.2.0
Summary: A canvas library with GUI elements for creating interactive applications
Author: Simon Lab
License: MIT
Project-URL: Homepage, https://github.com/simonlav24/CanvaSim
Classifier: Development Status :: 3 - Alpha
Classifier: Intended Audience :: Developers
Classifier: License :: OSI Approved :: MIT License
Classifier: Programming Language :: Python :: 3
Classifier: Programming Language :: Python :: 3.8
Classifier: Programming Language :: Python :: 3.9
Classifier: Programming Language :: Python :: 3.10
Classifier: Programming Language :: Python :: 3.11
Classifier: Programming Language :: Python :: 3.12
Classifier: Topic :: Multimedia :: Graphics
Classifier: Topic :: Software Development :: Libraries :: Python Modules
Requires-Python: >=3.8
License-File: LICENSE
Requires-Dist: pygame-ce
Dynamic: license-file
